crex/__init__.py
crex/main.py
crex-0.0.1.dist-info/METADATA
crex-0.0.1.dist-info/WHEEL
crex-0.0.1.dist-info/licenses/LICENSE
crex-0.0.1.dist-info/RECORD
