Metadata-Version: 2.1
Name: crex
Version: 0.0.1
Summary: Library for crypto exchange
Project-URL: GitHub, https://github.com/miviskin/crex
Author-email: miviskin <miviskin@gmail.com>
License: Copyright (c) 2018 The Python Packaging Authority
License-File: LICENSE
Classifier: License :: OSI Approved :: MIT License
Classifier: Operating System :: OS Independent
Classifier: Programming Language :: Python :: 3
Requires-Python: >=3.7
